{
  "availableOn": [
    "PC"
  ],
  "averageRating": 3.4,
  "badges": [
    {
      "type": 8
    },
    {
      "type": 2
    },
    {
      "type": 9
    }
  ],
  "bundledProductIds": [],
  "bundlesBySeed": [],
  "capabilities": {
    "XblLocalCoop": "Xbox local co-op (2-4)",
    "XblOnlineCoop": "Online co-op (2-4)",
    "XblLocalMultiPlayer": "Xbox local multiplayer (2-4)",
    "XblOnlineMultiPlayer": "Online multiplayer  (2-4)",
    "XblCrossPlatformMultiPlayer": "Xbox cross-platform multiplayer",
    "SinglePlayer": "Single player",
    "XblCrossPlatformCoop": "Xbox cross-platform co-op",
    "XblAchievements": "Xbox achievements"
  },
  "categories": [
    "Family & kids"
  ],
  "contentRating": {
    "boardName": "ESRB",
    "description": "For all ages",
    "disclaimers": [],
    "descriptors": [],
    "imageUri": "https://store-images.microsoft.com/image/global.23456.image.87f616db-3cfc-4611-b3b8-c57bbb87de71.7e7baf95-3edb-4b7c-a960-75e7537b07c9",
    "imageLinkUri": "https://www.esrb.org/ratings-guide/",
    "interactiveDescriptions": [],
    "rating": "EVERYONE",
    "ratingAge": 1,
    "ratingDescription": "For all ages"
  },
  "description": "Please note that friend invites are not currently supported for online play. This is being investigated and we hope to update the game in due course. Online matchmaking is available.\r\n\r\nOvercooked returns with a brand-new helping of chaotic cooking action! Journey back to the Onion Kingdom and assemble your team of chefs in classic couch co-op or online play for up to four players. Hold onto your aprons … it’s time to save the world (again!)\r\n\r\nOut of the frying pan, into the fire…\r\n\r\nYou’ve saved the world from the Ever Peckish. Now a new threat has arisen and it’s time to get back in the kitchen to stave off the hunger of The Unbread!\r\n\r\nONLINE/LOCAL MULTIPLAYER MADNESS- You’ll knead to work together (or against each other) to get the highest score in chaotic local and online multiplayer.\r\n\r\nFEAST YOUR EYES ON THIS- Journey across a brand new overworld map by land, sea and air. Get cooking in new themes ranging from sushi restaurants, magic schools, mines and even alien planets!\r\n\r\nWHET YOUR APPETITE! - Travel the land cooking up a range of new recipes that are sure to cater to any tastes, including sushi, cakes, burgers and pizzas.\r\n\r\nROMAINE CALM! - Travel through teleporters, across moving platforms and save time by throwing ingredients across dynamic kitchens that shift and evolve. Some kitchens even whisk your chefs away to new locations.",
  "developerName": "Ghost Town Games and Team17 Digital Ltd",
  "editions": [],
  "hasAddOns": true,
  "includedWithPassesProductIds": [
    "CFQ7TTC0K5DJ",
    "CFQ7TTC0KGQ8",
    "CFQ7TTC0P85B"
  ],
  "legalNotices": [
    "DataSharingDisclaimer",
    "InAppPurchase",
    "HasFirstPartyIAP",
    "XboxLiveGoldRequiredForOnline"
  ],
  "maxInstallSize": 8662454272,
  "optimalSatisfyingPassId": "CFQ7TTC0P85B",
  "optimalSkuId": "0010",
  "preferredSkuId": "0010",
  "productFamily": "Games",
  "productId": "9PGB72NFG5JN",
  "productKind": "Game",
  "publisherName": "Team17 Digital Ltd",
  "ratingCount": 278,
  "releaseDate": "2020-04-02T00:00:00.0000000Z",
  "shortDescription": "Overcooked returns with a brand-new helping of chaotic cooking action! Journey back to the Onion Kingdom and assemble your team of chefs in classic couch co-op or online play for up to four players. Hold onto your aprons … it’s time to save the world (again!)",
  "showSupportedLanguageDisclaimer": false,
  "specificPrices": {
    "purchaseable": [
      {
        "skuId": "0010",
        "availabilityId": "9QXWVQXGFBRQ",
        "discountPercentage": 0,
        "eligibilityInfo": {
          "eligibility": "None",
          "type": "Unknown"
        },
        "availabilityActions": [
          "Details",
          "Fulfill",
          "Purchase",
          "Browse",
          "Curate",
          "Redeem"
        ],
        "endDateUtc": "12/16/2027 09:59:59",
        "hasXPriceOffer": false,
        "listPrice": 24.99,
        "msrp": 24.99,
        "currency": "USD"
      },
      {
        "skuId": "0010",
        "availabilityId": "9Z4X2V8G9PPX",
        "discountPercentage": 20.008003,
        "eligibilityInfo": {
          "eligibility": "Remediation",
          "type": "PCGamePass",
          "productId": "CFQ7TTC0KGQ8"
        },
        "availabilityActions": [
          "Details",
          "Fulfill",
          "Purchase",
          "Browse",
          "Curate"
        ],
        "hasXPriceOffer": false,
        "listPrice": 19.99,
        "msrp": 24.99,
        "currency": "USD"
      }
    ],
    "giftable": [
      {
        "skuId": "0010",
        "availabilityId": "9W50PLVS2GX9",
        "discountPercentage": 20.008003,
        "eligibilityInfo": {
          "eligibility": "Remediation",
          "type": "PCGamePass",
          "productId": "CFQ7TTC0KGQ8"
        },
        "availabilityActions": [
          "Details",
          "Fulfill",
          "Browse",
          "Curate",
          "Gift"
        ],
        "hasXPriceOffer": false,
        "listPrice": 19.99,
        "msrp": 24.99,
        "currency": "USD"
      },
      {
        "skuId": "0010",
        "availabilityId": "9QS89G8MC5J2",
        "discountPercentage": 0,
        "eligibilityInfo": {
          "eligibility": "None",
          "type": "Unknown"
        },
        "availabilityActions": [
          "Details",
          "Fulfill",
          "Browse",
          "Curate",
          "Gift"
        ],
        "endDateUtc": "12/16/2027 09:59:59",
        "hasXPriceOffer": false,
        "listPrice": 24.99,
        "msrp": 24.99,
        "currency": "USD"
      }
    ],
    "totalPurchaseablePricesCount": 2
  },
  "title": "Overcooked! 2",
  "passMetadataByPassProductId": {
    "CFQ7TTC0K5DJ": {
      "entryDateUTC": "2025-10-01T16:00:00Z"
    },
    "CFQ7TTC0KHS0": {
      "entryDateUTC": "2025-10-01T16:00:00Z"
    },
    "CFQ7TTC0KGQ8": {
      "entryDateUTC": "2020-04-02T00:00:00Z"
    },
    "CFQ7TTC0P85B": {
      "entryDateUTC": "2025-10-01T16:00:00Z"
    }
  },
  "isAvailableOnGarrison": true,
  "hasUbisoftCrossEntitlementProduct": false
}