{
  "availableOn": [
    "XboxOne",
    "XboxSeriesX"
  ],
  "averageRating": 4,
  "badges": [
    {
      "type": 11
    }
  ],
  "bundledProductIds": [],
  "bundlesBySeed": [],
  "capabilities": {
    "XblOnlineMultiPlayer": "Online multiplayer  (2-8)",
    "Capability4k": "4K Ultra HD",
    "CapabilityXboxEnhanced": "Xbox One X Enhanced"
  },
  "categories": [
    "Racing & flying"
  ],
  "contentRating": {
    "boardName": "ESRB",
    "description": "For ages 10 and up",
    "disclaimers": [],
    "descriptors": [
      "Mild Violence",
      "Mild Suggestive Themes"
    ],
    "imageUri": "https://store-images.microsoft.com/image/global.56093.image.e3da543f-ed61-47ce-bc12-683dab90c502.5e57d206-3b82-4a7b-9b98-d1548cd450a8",
    "imageLinkUri": "https://www.esrb.org/ratings-guide/",
    "interactiveDescriptions": [
      "Users Interact"
    ],
    "rating": "EVERYONE 10+",
    "ratingAge": 10,
    "ratingDescription": "For ages 10 and up"
  },
  "description": "Welcome back to Paradise City! Make action your middle name as you rule the streets in Burnout™ Paradise Remastered. Tear up the town from hectic downtown avenues to wild mountain roads. Relive the high-octane stunts and wanton destruction of one of the greatest arcade-driving games ever!\r\n\r\nBurnout Paradise Remastered provides the ultimate driving playground for you and your friends to play online. This remaster includes all addons from the Year of Paradise, including the Big Surf Island update, meticulously recreated and ready to wreck in 4K on the Xbox One X.\r\n\r\nExplore Paradise City with Friends-\r\nBurn rubber and shred metal across the open roads of Paradise City while discovering jumps, stunts, and shortcuts. Blaze your path to glory in unique events, using your knowledge of the city to find the fastest routes and get the drop on rivals. Wreck your friends online or join forces to demolish hundreds of online challenges.\r\n\r\nBreak the Rules and Crash Anywhere at Any Time \r\nThrow out that driver’s handbook and set speed and destruction records all over town. Track how many you own, and prove your demolition dominance against your friends. Send your car launching, spinning, and scraping through the city, smashing through traffic and leaving a very expensive trail of wreckage in your rearview.\r\n\r\nThe Definitive Burnout Paradise Experience\r\nThe remaster delivers the complete original game and all additional downloadable content ever released with a range of technical enhancements for greater visual fidelity and authenticity, including high resolution textures and more. It plays natively in 1080p on the Xbox One and in stunning 4K at 60fps on the Xbox One X.\r\n\r\nConditions and restrictions apply. See https://www.ea.com/games/burnout/burnout-paradise-remastered/disclaimers for details.",
  "developerName": "Stellar Entertainment",
  "editions": [],
  "hasAddOns": false,
  "includedWithPassesProductIds": [
    "CFQ7TTC0K5DH"
  ],
  "legalNotices": [
    "DataSharingDisclaimer",
    "XboxLiveGoldRequiredForOnline"
  ],
  "maxInstallSize": 8221306880,
  "optimalSatisfyingPassId": "CFQ7TTC0K5DH",
  "optimalSkuId": "0001",
  "preferredSkuId": "0001",
  "productFamily": "Games",
  "productId": "BQMQ3K1BLV1T",
  "productKind": "Game",
  "publisherName": "Electronic Arts",
  "ratingCount": 261,
  "releaseDate": "2018-03-16T00:00:00.0000000Z",
  "shortDescription": "Welcome back to Paradise City! Make action your middle name as you rule the streets in Burnout™ Paradise Remastered! Tear it up in the ultimate driving playground, from hectic downtown avenues to the wild mountain roads. Relive the high-octane stunts and wanton destruction of one of the greatest arcade-driving games ever!",
  "showSupportedLanguageDisclaimer": false,
  "specificPrices": {
    "purchaseable": [
      {
        "skuId": "0001",
        "availabilityId": "9RF6NC3464NK",
        "discountPercentage": 0,
        "eligibilityInfo": {
          "eligibility": "None",
          "type": "Unknown"
        },
        "availabilityActions": [
          "Details",
          "Fulfill",
          "Purchase",
          "Browse",
          "Curate",
          "Redeem"
        ],
        "endDateUtc": "12/30/2799 23:59:59",
        "hasXPriceOffer": false,
        "listPrice": 19.99,
        "msrp": 19.99,
        "currency": "USD"
      },
      {
        "skuId": "0001",
        "availabilityId": "B3BKTFT3KX7Q",
        "discountPercentage": 10.005003,
        "eligibilityInfo": {
          "eligibility": "Remediation",
          "type": "EAAccess",
          "productId": "CFQ7TTC0K5DH"
        },
        "availabilityActions": [
          "Details",
          "Fulfill",
          "Purchase",
          "Browse",
          "Curate"
        ],
        "hasXPriceOffer": false,
        "listPrice": 17.99,
        "msrp": 19.99,
        "currency": "USD"
      }
    ],
    "giftable": [
      {
        "skuId": "0001",
        "availabilityId": "9XBSP5C7DHBT",
        "discountPercentage": 10.005003,
        "eligibilityInfo": {
          "eligibility": "Remediation",
          "type": "EAAccess",
          "productId": "CFQ7TTC0K5DH"
        },
        "availabilityActions": [
          "Details",
          "Fulfill",
          "Browse",
          "Curate",
          "Gift"
        ],
        "hasXPriceOffer": false,
        "listPrice": 17.99,
        "msrp": 19.99,
        "currency": "USD"
      },
      {
        "skuId": "0001",
        "availabilityId": "B2NB1VDS9Q67",
        "discountPercentage": 0,
        "eligibilityInfo": {
          "eligibility": "None",
          "type": "Unknown"
        },
        "availabilityActions": [
          "Details",
          "Fulfill",
          "Browse",
          "Curate",
          "Gift"
        ],
        "endDateUtc": "12/30/2799 23:59:59",
        "hasXPriceOffer": false,
        "listPrice": 19.99,
        "msrp": 19.99,
        "currency": "USD"
      }
    ],
    "totalPurchaseablePricesCount": 2
  },
  "title": "Burnout™ Paradise Remastered",
  "passMetadataByPassProductId": {
    "CFQ7TTC0K5DH": {
      "entryDateUTC": "2020-11-06T09:00:00Z"
    }
  },
  "isAvailableOnGarrison": false,
  "hasUbisoftCrossEntitlementProduct": false
}