{
  "accessibilityCapabilities": {
    "audio": [
      "Surround sound"
    ],
    "gameplay": [],
    "input": [
      "Playable without rapid button presses",
      "Playable without motion controls",
      "Playable without touch controls"
    ],
    "publisherInformationUri": "https://www.ea.com/able/resources/pvz/pvz-battle-for-neighborville/xbox-one",
    "visual": [
      "Color alternatives",
      "Camera comfort"
    ]
  },
  "availableOn": [
    "XboxOne",
    "XboxSeriesX",
    "XCloud"
  ],
  "averageRating": 3.3,
  "badges": [
    {
      "type": 11
    }
  ],
  "bundledProductIds": [],
  "bundlesBySeed": [
    "9PLCCSXK3H05",
    "C4RR6ST0P1X7"
  ],
  "capabilities": {
    "XblLocalCoop": "Xbox local co-op (2-2)",
    "XblOnlineCoop": "Online co-op (2-24)",
    "XblLocalMultiPlayer": "Xbox local multiplayer (2-2)",
    "XblOnlineMultiPlayer": "Online multiplayer  (2-24)",
    "Capability4k": "4K Ultra HD",
    "CapabilityHDR": "HDR10",
    "SharedSplitScreen": "Shared/split screen",
    "GameStreaming": "Cloud enabled",
    "FPSBoostEnabledXS": "FPS Boost Series X | S"
  },
  "categories": [
    "Shooter"
  ],
  "contentRating": {
    "boardName": "ESRB",
    "description": "For ages 10 and up",
    "disclaimers": [],
    "descriptors": [
      "Fantasy Violence",
      "Comic Mischief"
    ],
    "imageUri": "https://store-images.microsoft.com/image/global.56093.image.e3da543f-ed61-47ce-bc12-683dab90c502.5e57d206-3b82-4a7b-9b98-d1548cd450a8",
    "imageLinkUri": "https://www.esrb.org/ratings-guide/",
    "interactiveDescriptions": [
      "Users Interact",
      "In-Game Purchases"
    ],
    "rating": "EVERYONE 10+",
    "ratingAge": 10,
    "ratingDescription": "For ages 10 and up"
  },
  "description": "Welcome to Neighborville, where all is well. Except that a crazy new coniferous conflict between brain-less and botanicals is brewing! What are you gonna do – call the crops? Soil your plants? Prepare to kick some grass in a plant-on-zombie conflict that will take you to the outer edges of Neighborville and back again.\r\n\r\n\r\nCustomize Every Character for Battle\r\nJoin the newest bloom in the age-old battle between plants and zombies with 20 fully customizable classes at launch, including a Team Play class for each faction. Bring the unique abilities of each character class to six PvP modes, including the new Battle Arena, and experience the unbeleafable thrills of combat. \r\n\r\nVenture to the Outer Edges of Neighborville\r\nThe tension across the terra has expanded with three free-roam regions and one PvE mode that extend beyond the town of Neighborville. Squad up with up to three friends in the Giddy Park social region and take back Weirding Woods, Mount Steep, and Neighborville Town Centre. It’s grow time!\r\n\r\nPlay with Your Favorite People, in Every Mode \r\nJoin forces with other players to experience split-screen couch co-op in every mode. Connect with up to three players and battle through flourishing free-roam regions or jump into the fray with up to 24 players in online multiplayer across a gigantic suburban skirmish.  \r\n\r\nConditions and restrictions apply.  See WWW.EA.COM/LEGAL for details.",
  "developerName": "EAV",
  "editions": [],
  "hasAddOns": true,
  "includedWithPassesProductIds": [
    "CFQ7TTC0K5DH"
  ],
  "legalNotices": [
    "LegalNoticeCallisto",
    "DataSharingDisclaimer",
    "InAppPurchase",
    "HasFirstPartyIAP",
    "XboxLiveGoldRequiredForOnline"
  ],
  "maxInstallSize": 32994246656,
  "optimalSatisfyingPassId": "CFQ7TTC0K5DH",
  "optimalSkuId": "0001",
  "preferredSkuId": "0001",
  "productFamily": "Games",
  "productId": "C4HZC7LJG6PX",
  "productKind": "Game",
  "publisherName": "Electronic Arts",
  "ratingCount": 451,
  "releaseDate": "2019-10-18T04:00:00.0000000Z",
  "shortDescription": "Kick some grass in Plants vs. Zombies Battle for Neighborville, the wackiest shooter yet! Unearth 20 fully customizable character classes at launch in one social region, three free-roam regions, one PvE mode, six PvP modes, including Battle Arena, and more!",
  "showSupportedLanguageDisclaimer": false,
  "specificPrices": {
    "purchaseable": [
      {
        "skuId": "0001",
        "availabilityId": "B4Z7QD7T3C95",
        "discountPercentage": 0,
        "eligibilityInfo": {
          "eligibility": "None",
          "type": "Unknown"
        },
        "availabilityActions": [
          "Details",
          "Fulfill",
          "Purchase",
          "Browse",
          "Curate",
          "Redeem"
        ],
        "endDateUtc": "10/06/2025 23:59:59",
        "hasXPriceOffer": false,
        "listPrice": 19.99,
        "msrp": 19.99,
        "currency": "USD"
      },
      {
        "skuId": "0001",
        "availabilityId": "9P2WSBF4Q59L",
        "discountPercentage": 10.005003,
        "eligibilityInfo": {
          "eligibility": "Remediation",
          "type": "EAAccess",
          "productId": "CFQ7TTC0K5DH"
        },
        "availabilityActions": [
          "Details",
          "Fulfill",
          "Purchase",
          "Browse",
          "Curate"
        ],
        "hasXPriceOffer": false,
        "listPrice": 17.99,
        "msrp": 19.99,
        "currency": "USD"
      }
    ],
    "giftable": [
      {
        "skuId": "0001",
        "availabilityId": "B4BNS9M7CMJ6",
        "discountPercentage": 10.005003,
        "eligibilityInfo": {
          "eligibility": "Remediation",
          "type": "EAAccess",
          "productId": "CFQ7TTC0K5DH"
        },
        "availabilityActions": [
          "Details",
          "Fulfill",
          "Browse",
          "Curate",
          "Gift"
        ],
        "hasXPriceOffer": false,
        "listPrice": 17.99,
        "msrp": 19.99,
        "currency": "USD"
      },
      {
        "skuId": "0001",
        "availabilityId": "9W4TD38VTPZK",
        "discountPercentage": 0,
        "eligibilityInfo": {
          "eligibility": "None",
          "type": "Unknown"
        },
        "availabilityActions": [
          "Details",
          "Fulfill",
          "Browse",
          "Curate",
          "Gift"
        ],
        "endDateUtc": "10/06/2025 23:59:59",
        "hasXPriceOffer": false,
        "listPrice": 19.99,
        "msrp": 19.99,
        "currency": "USD"
      }
    ],
    "totalPurchaseablePricesCount": 2
  },
  "title": "Plants vs. Zombies: Battle for Neighborville™",
  "xCloudProperties": {
    "xCloudId": "PVZBATTLEFORNEIGHBORVILLE",
    "xboxTitleId": 749311689,
    "supportsTouch": false
  },
  "passMetadataByPassProductId": {
    "CFQ7TTC0K5DH": {
      "entryDateUTC": "2020-11-06T09:00:00Z"
    }
  },
  "xCloudPropertiesV2": {
    "xCloudId": "PVZBATTLEFORNEIGHBORVILLE",
    "xboxTitleId": 749311689,
    "programs": [
      "GPULTIMATE",
      "CALLISTO",
      "IO",
      "GANYMEDE"
    ],
    "supportedInputTypes": [
      "Controller"
    ],
    "supportsTouch": false
  },
  "isAvailableOnGarrison": false,
  "hasUbisoftCrossEntitlementProduct": false
}