{
  "general": {
    "id": 7849,
    "game_modes": [
      {
        "id": 1,
        "name": "Single player"
      }
    ],
    "genres": [
      {
        "id": 5,
        "name": "Shooter"
      }
    ],
    "involved_companies": [
      {
        "id": 18314,
        "company": {
          "id": 722,
          "name": "343 Industries"
        },
        "developer": true,
        "publisher": false
      },
      {
        "id": 18315,
        "company": {
          "id": 2169,
          "name": "Vanguard Entertainment"
        },
        "developer": true,
        "publisher": false
      },
      {
        "id": 18316,
        "company": {
          "id": 128,
          "name": "Microsoft"
        },
        "developer": false,
        "publisher": true
      }
    ],
    "name": "Halo: Spartan Strike",
    "player_perspectives": [
      {
        "id": 3,
        "name": "Bird view / Isometric"
      }
    ],
    "themes": [
      {
        "id": 1,
        "name": "Action"
      },
      {
        "id": 18,
        "name": "Science fiction"
      },
      {
        "id": 39,
        "name": "Warfare"
      }
    ],
    "url": "https://www.igdb.com/games/halo-spartan-strike",
    "game_type": 0
  },
  "release_dates": [
    {
      "id": 101256,
      "date": 1429142400,
      "platform": 6
    },
    {
      "id": 101257,
      "date": 1429142400,
      "platform": 74
    },
    {
      "id": 101258,
      "date": 1429142400,
      "platform": 39
    },
    {
      "id": 121055,
      "date": 1429142400,
      "platform": 6
    }
  ]
}