{
  "basic_info": {
    "base_id": 27409,
    "specific_id": 27409,
    "title": "Narita Boy",
    "store_title": "Narita Boy",
    "pid": "9NT3FGQC1DFR",
    "alternate_xbox_id": null,
    "related_skus": [
      "9NBL782WBHK6"
    ],
    "sku_groups": [
      [
        "9NBL782WBHK6"
      ],
      [
        "9NT3FGQC1DFR"
      ]
    ],
    "original_release_date": "2021-03-30",
    "release_date": null,
    "platforms": [
      "PC"
    ]
  },
  "availabilities": [
    {
      "PC": {
        "added": "2021-03-30",
        "removed": "2022-04-01"
      },
      "Ultimate": {
        "added": "2021-03-30",
        "removed": "2022-04-01"
      }
    }
  ],
  "flags": {
    "indie": true,
    "first_party": false,
    "f2p": false
  },
  "xbox_store_meta": {
    "capabilities": {
      "SinglePlayer": "Single player",
      "PcGamePad": "PC Game Pad",
      "XblAchievements": "Xbox achievements",
      "XblPresence": "Xbox presence",
      "XblClubs": "Xbox clubs",
      "XblCloudSaves": "Xbox cloud saves"
    },
    "categories": [
      "Action & adventure",
      "Platformer"
    ],
    "publisher": "Team17 ",
    "developer": "Studio Koba"
  },
  "igdb_meta": {
    "main": {
      "id": 27409,
      "name": "Narita Boy",
      "url": "https://www.igdb.com/games/narita-boy",
      "publishers": [
        "Team17"
      ],
      "developers": [
        "Studio Koba"
      ],
      "genres": [
        "Platform",
        "Role-playing (RPG)",
        "Strategy",
        "Adventure",
        "Indie",
        "Arcade"
      ],
      "themes": [
        "Action",
        "Mystery"
      ],
      "game_modes": [
        "Single player"
      ],
      "player_perspectives": [
        "Side view"
      ]
    }
  },
  "steam_store_meta": {}
}