{
  "basic_info": {
    "base_id": 80853,
    "specific_id": 80853,
    "title": "Metro 2033 Redux",
    "store_title": "Metro 2033 Redux",
    "pid": "BPPTRQZRJ341",
    "alternate_xbox_id": null,
    "related_skus": [],
    "sku_groups": [
      [
        "BPPTRQZRJ341"
      ]
    ],
    "original_release_date": "2014-08-26",
    "release_date": "2014-08-26",
    "platforms": [
      "XboxOne",
      "XboxSeriesX"
    ]
  },
  "availabilities": [
    {}
  ],
  "flags": {
    "indie": false,
    "first_party": false,
    "f2p": false
  },
  "xbox_store_meta": {
    "capabilities": {
      "FPSBoostEnabledXS": "FPS Boost Series X | S"
    },
    "categories": [
      "Shooter"
    ],
    "publisher": "Deep Silver",
    "developer": "4A Games"
  },
  "igdb_meta": {
    "main": {
      "id": 80853,
      "name": "Metro 2033 Redux",
      "url": "https://www.igdb.com/games/metro-2033-redux",
      "publishers": [
        "Deep Silver",
        "Koch Media"
      ],
      "developers": [
        "4A Games"
      ],
      "genres": [
        "Shooter",
        "Role-playing (RPG)",
        "Adventure"
      ],
      "themes": [
        "Action",
        "Science fiction",
        "Horror",
        "Thriller",
        "Survival",
        "Stealth",
        "Warfare"
      ],
      "game_modes": [
        "Single player"
      ],
      "player_perspectives": [
        "First person"
      ],
      "engine": [
        "4A Engine"
      ],
      "game_type": "remaster",
      "release_dates": {
        "release_date": "2014-08-26",
        "PC": {
          "release_date_ea": null,
          "release_date_1_0": "2014-08-28"
        },
        "Xbox One": {
          "release_date_ea": null,
          "release_date_1_0": "2014-08-26"
        },
        "Xbox Series X|S": {
          "release_date_ea": null,
          "release_date_1_0": null
        },
        "Xbox 360": {
          "release_date_ea": null,
          "release_date_1_0": null
        }
      }
    }
  },
  "steam_store_meta": {}
}