{
  "basic_info": {
    "base_id": 11288,
    "specific_id": 11288,
    "title": "Mega Coin Squad",
    "store_title": "Mega Coin Squad",
    "pid": "BRM6SS1W7LDK",
    "alternate_xbox_id": null,
    "related_skus": [],
    "sku_groups": [
      [
        "BRM6SS1W7LDK"
      ]
    ],
    "original_release_date": "2014-08-15",
    "release_date": null,
    "platforms": [
      "XboxOne",
      "XboxSeriesX"
    ]
  },
  "availabilities": [
    {}
  ],
  "flags": {
    "indie": true,
    "first_party": false,
    "f2p": false
  },
  "xbox_store_meta": {
    "capabilities": {
      "XblLocalMultiPlayer": "Xbox local multiplayer (2-4)"
    },
    "categories": [
      "Action & adventure",
      "Family & kids",
      "Fighting",
      "Platformer"
    ],
    "publisher": "Adult Swim Games",
    "developer": "Big Pixel Studios"
  },
  "igdb_meta": {
    "main": {
      "id": 11288,
      "name": "Mega Coin Squad",
      "url": "https://www.igdb.com/games/mega-coin-squad",
      "publishers": [
        "Adult Swim Games"
      ],
      "developers": [
        "Big Pixel Studios"
      ],
      "genres": [
        "Fighting",
        "Platform",
        "Indie",
        "Arcade"
      ],
      "themes": [
        "Action"
      ],
      "game_modes": [
        "Single player",
        "Multiplayer",
        "Split screen"
      ],
      "player_perspectives": [
        "Side view"
      ]
    }
  },
  "steam_store_meta": {}
}